[
  {
    "text": "The text can be answered with a proper name.",
    "intended_class": "LOC"
  },
  {
    "text": "The text asks for a person or a place.",
    "intended_class": "HUM"
  },
  {
    "text": "The text expects a short, factual answer.",
    "intended_class": "NUM"
  },
  {
    "text": "The text asks for a person.",
    "intended_class": "HUM"
  },
  {
    "text": "The text asks for an abbreviation.",
    "intended_class": "ABBR"
  },
  {
    "text": "The text asks for a location.",
    "intended_class": "LOC"
  },
  {
    "text": "The text asks for a number.",
    "intended_class": "NUM"
  },
  {
    "text": "The text asks for a definition or explanation.",
    "intended_class": "ABBR"
  }
]